control_unit.v
`timescale 1ns / 1ps
module control_unit(clk, rst, ram_data, ram_read_en, ram_write_en, ram_address, opcode, alu_in_A, alu_in_B, alu_out, overflow, zero, negative);

input clk, rst, overflow, zero, negative ;   		// clock, reset
input [7:0] alu_out;

output reg ram_read_en, ram_write_en;
output reg [7:0] alu_in_A, alu_in_B;
output reg [3:0] opcode;
output reg [3:0] ram_address;

// 相当于control_unit和ram之间的databus
inout [7:0] ram_data;


reg [7:0] Register[0:3];
reg [3:0] PC;
reg [2:0] state;

// 仅做仿真时观察波形使用：begin
wire [7:0] test_Register0, test_Register1, test_Register2, test_Register3; 
assign test_Register0 = Register[0];
assign test_Register1 = Register[1];
assign test_Register2 = Register[2];
assign test_Register3 = Register[3];
// 仅做仿真时观察波形使用：end
// 有关仿真时数组再iverilog的显示问题，参考了
// https://stackoverflow.com/questions/20317820/icarus-verilog-dump-memory-array-dumpvars
// 原因：iverilog 仿真时就是不能 dump 数组

// 相当于control_unit和ram之间的databus
assign ram_data = (ram_write_en)? Register[0]:8'hzz;

// instruction code
parameter 	HALT     = 4'b0000,
			LOAD_A   = 4'b0010,
			LOAD_B   = 4'b0001,
			STORE_A  = 4'b0100,
			ADD      = 4'b1000,
			SUB      = 4'b1001,
			JUMP     = 4'b1010,
			JUMP_NEG = 4'b1011,
			WIDTH    = 8,
			MSB      = WIDTH - 1;

// state encoding one-hot			 
parameter	S0 = 3'b001,
			S1 = 3'b010,
			S2 = 3'b100;

initial
	begin
		state = S0;
		PC = 4'b0000;
		ram_address = 4'b0000;
		opcode = HALT;
		alu_in_A	= 8'b0000_0000;
		alu_in_B 	= 8'b0000_0000;
		Register[0] = 8'b0000_0000;
		Register[1] = 8'b0000_0000;
		Register[2] = 8'b0000_0000;
		Register[3] = 8'b0000_0000;
		ram_read_en = 1'b0;
		ram_write_en = 1'b0;

		//通用寄存器初始化
	end
    


always@(posedge clk)
begin
	case(state)
	// 取指令
	S0: begin
		ram_address <= PC;
		ram_read_en <= 1'b1;
		ram_write_en<= 1'b0;
		opcode <= ram_data[7:4];
		if (opcode == HALT || rst) begin
			state <= S0;
			
		end else begin
			PC <= PC + 1;
			state <= S1;

		end
	end
	// 指令译码(对号入座)和执行指令
	S1: begin
		if ((opcode == LOAD_A) || (opcode == LOAD_B)) begin
			ram_address <= ram_data[3:0];
			ram_read_en <= 1'b1;
			ram_write_en<= 1'b0;
			state <= S2;

			
		end else if ((opcode == ADD) || (opcode == SUB)) begin
			alu_in_B <= Register[ram_data[3:2]];
			alu_in_A <= Register[ram_data[1:0]];
			state <= S2;
			
			
		end else if (opcode == JUMP) begin
			PC <= ram_data[3:0];
			state <= S2;

		end else if (opcode == JUMP_NEG) begin
			PC <= negative ? ram_data[3:0] : (PC);
			state <= S2;
			
		end else if (opcode == STORE_A) begin
			ram_address <= ram_data[3:0];
			ram_read_en <= 1'b0;
			ram_write_en <= 1'b1;
			state <= S2;

		end else begin
			state <= S0;
		end
		
	end
	// 写入寄存器或RAM以及准备复位
	S2: begin
		case (opcode)
			LOAD_A: begin 
				Register[0] <= ram_data[7:0];
				ram_address <= PC;
				state <= S0;
			end
			LOAD_B: begin
				Register[1] <= ram_data[7:0];
				ram_address <= PC;
				state <= S0;
			end
			ADD: begin
				Register[ram_data[1:0]] <= alu_out;
				ram_address <= PC;
				state <= S0; 
			end
			SUB: begin
				Register[ram_data[1:0]] <= alu_out;
				ram_address <= PC;
				state <= S0;
				
			end
			STORE_A: begin
				ram_read_en <= 1'b1;
				ram_write_en <= 1'b0;
				ram_address <= PC;
				
				state <= S0;
			end
			JUMP: begin
				ram_address <= PC;
				state <= S0;
			end
			JUMP_NEG: begin
				ram_address <= PC;
				state <= S0;
			end

			default: state <= S0;
		endcase
	end

	default: begin
		state <= S0;
		ram_read_en  <= 1'b0;
		ram_write_en <= 1'b0;
		ram_address <= 4'b0000;
		opcode <= HALT;
	end
endcase
end

endmodule

ram.v
`timescale 1ns / 1ps
/////////////////////////////////////////////////////////////
module ram(ram_data, ram_read_en, ram_write_en, ram_address);

input ram_read_en, ram_write_en;
input [3:0] ram_address;

inout [7:0] ram_data;

reg [7:0] ram[0:15];

//仅做仿真时观察波形使用：begin
wire [7:0] ram_13; 
assign ram_13 = ram[13];
//仅做仿真时观察波形使用：end

// //第一个程序，计算机速成课episode 7
// //3+14 = 17
// initial 
// 	begin
// 		ram[0] = 8'b0010_1110; // LOAD_A 14
// 		ram[1] = 8'b0001_1111; // LOAD_B 15
// 		ram[2] = 8'b1000_0100; // ADD B A
// 		ram[3] = 8'b0100_1101; // STORE_A 13
// 		ram[4] = 8'b0000_0000;
// 		ram[5] = 8'b0000_0000;
// 		ram[6] = 8'b0000_0000;
// 		ram[7] = 8'b0000_0000;
// 		ram[8] = 8'b0000_0000;
// 		ram[9] = 8'b0000_0000;
// 		ram[10]= 8'b0000_0000;
// 		ram[11]= 8'b0000_0000;
// 		ram[12]= 8'b0000_0000;
// 		ram[13]= 8'b0000_0000;
// 		ram[14]= 8'b0000_0011; // 3
// 		ram[15]= 8'b0000_1110; // 14
// 	end

// //第二个程序，计算机速成课episode 8
// //1+1,2+1,...
// initial 
// 	begin
// 		ram[0] = 8'b0010_1110; // LOAD_A 14
// 		ram[1] = 8'b0001_1111; // LOAD_B 15
// 		ram[2] = 8'b1000_0100; // ADD B A
// 		ram[3] = 8'b0100_1101; // STORE_A 13
// 		ram[4] = 8'b1010_0010; // JUMP 2
// 		ram[5] = 8'b0000_0000;
// 		ram[6] = 8'b0000_0000;
// 		ram[7] = 8'b0000_0000;
// 		ram[8] = 8'b0000_0000;
// 		ram[9] = 8'b0000_0000;
// 		ram[10]= 8'b0000_0000;
// 		ram[11]= 8'b0000_0000;
// 		ram[12]= 8'b0000_0000;
// 		ram[13]= 8'b0000_0000;
// 		ram[14]= 8'b0000_0001; // 1
// 		ram[15]= 8'b0000_0001; // 1
// 	end

// 第三个程序，计算机速成课episode 8
// 11 mod 5 == 1
initial 
	begin
		ram[0] = 8'b0010_1110; // LOAD_A 14
		ram[1] = 8'b0001_1111; // LOAD_B 15
		ram[2] = 8'b1001_0100; // SUB B A
		ram[3] = 8'b1011_0101; // JUMP_NEG 5
		ram[4] = 8'b1010_0010; // JUMP 2
		ram[5] = 8'b1000_0100; // ADD B A
		ram[6] = 8'b0100_1101; // STORE_A 13
		ram[7] = 8'b0000_0000; // HALT
		ram[8] = 8'b0000_0000;
		ram[9] = 8'b0000_0000;
		ram[10]= 8'b0000_0000;
		ram[11]= 8'b0000_0000;
		ram[12]= 8'b0000_0000;
		ram[13]= 8'b0000_0000;
		ram[14]= 8'b0000_1011; // 11
		ram[15]= 8'b0000_0101; // 5
	end


assign ram_data = (ram_read_en)? ram[ram_address]:8'hzz;		// read data from RAM

//尝试了always @(posedge ram_write_en) //失败，发现赋值结果为高阻态
always @(ram_write_en or ram_data) begin	// write data to RAM
	if (ram_write_en) ram[ram_address] <= ram_data;
end

endmodule

alu.v
`timescale 1ns / 1ps
//////////////////////////////////////////////////////////////
module alu(opcode, alu_in_A, alu_in_B, alu_out, overflow, zero, negative);//  arithmetic logic unit
input [3:0] opcode;
input [7:0] alu_in_A, alu_in_B;
output reg [7:0] alu_out;
output reg overflow;
output reg zero;
output reg negative;

reg extra;

parameter 	HALT     = 4'b0000,
			LOAD_A   = 4'b0010,
			LOAD_B   = 4'b0001,
			STORE_A  = 4'b0100,
			ADD      = 4'b1000,
			SUB      = 4'b1001,
			JUMP     = 4'b1010,
			JUMP_NEG = 4'b1011,
			WIDTH    = 8,
			MSB      = WIDTH - 1;


initial
	begin
		alu_out = 8'b00000000;
		overflow = 1'b0;
		zero = 1'b0;
		negative = 1'b0;
		extra = 1'b0;

		//通用寄存器初始化
	end

always @(*) begin
		case (opcode)
		ADD:
		begin
			{extra, alu_out} = {alu_in_A[MSB], alu_in_A} + {alu_in_B[MSB], alu_in_B};
			overflow  = ({extra, alu_out[MSB]} == 2'b01) || ({extra, alu_out[MSB]} == 2'b10);
			zero = alu_out ? 0 : 1;
			negative = alu_out[MSB];
		end
		SUB:
		begin
			if (!alu_in_B) begin
				alu_out = alu_in_A;
				overflow  = 1'b0;
				zero = alu_out ? 0 : 1;
				negative = alu_out[MSB];
			end else begin
				{extra, alu_out} = {alu_in_A[MSB], alu_in_A} + ~{alu_in_B[MSB], alu_in_B} + 9'b000000001;
				overflow  = ({extra, alu_out[MSB]} == 2'b01) || ({extra, alu_out[MSB]} == 2'b10);
				zero = alu_out ? 0 : 1;
				negative = alu_out[MSB];
			end
		end

		default:	alu_out = 8'bzzzz_zzzz;
		endcase
end

endmodule

core.v
`timescale 1ns / 1ps
module core(clk, rst);	// Top-level entity(except core-tb)
input clk, rst;

wire ram_read_en, ram_write_en;
wire overflow, zero, negative;

wire[7:0] ram_data;
wire[7:0] alu_in_A, alu_in_B, alu_out;
wire[3:0] opcode, ram_address;

//module alu(opcode, alu_in_A, alu_in_B, alu_out, overflow, zero, negative);
alu ALU(.opcode(opcode), .alu_in_A(alu_in_A), .alu_in_B(alu_in_B), .alu_out(alu_out), .overflow(overflow), .zero(zero), .negative(negative));

//module ram(ram_data, ram_read_en, ram_write_en, ram_address);
ram RAM(.ram_data(ram_data), .ram_read_en(ram_read_en), .ram_write_en(ram_write_en), .ram_address(ram_address));


//module control_unit(clk, rst, ram_data, ram_read_en, ram_write_en, ram_address, opcode, alu_in_A, alu_in_B, alu_out, overflow, zero, negative);
control_unit CONTROL_UNIT(.clk(clk), 
					.rst(rst), 
					.ram_data(ram_data), 
					.ram_read_en(ram_read_en), 
					.ram_write_en(ram_write_en), 
					.ram_address(ram_address), 
					.opcode(opcode), 
					.alu_in_A(alu_in_A), 
					.alu_in_B(alu_in_B), 
					.alu_out(alu_out), 
					.overflow(overflow), 
					.zero(zero), 
					.negative(negative)
					);
					

endmodule

core_testbench.v
`timescale 1ps / 1ps
module core_testbench; 

reg rst; 
reg clk; 

initial
	begin
    $dumpfile("test.vcd");
    $dumpvars(0,core1);
	end

initial
  begin
    clk <= 1'b0;
    # 150 ;
  repeat(9999)
  begin
    clk  = 1'b1;
    #50  clk  = 1'b0;
    #50  ;
  end
  clk  = 1'b1;
  # 50 ;
  end
initial
  begin
	  rst  = 1'b1  ;
	  # 100;
	  rst=1'b0;
	  # 9000 ;
  end
core core1(.clk(clk),.rst(rst));

initial
#1000000 $finish;
endmodule

第八集程序1仿真波形结果/test.vcd
$date
	Tue May 19 15:47:36 2020
$end
$version
	Icarus Verilog
$end
$timescale
	1ps
$end
$scope module core_testbench $end
$scope module core1 $end
$var wire 1 ! clk $end
$var wire 8 " ram_data [7:0] $end
$var wire 1 # rst $end
$var wire 1 $ zero $end
$var wire 1 % ram_write_en $end
$var wire 1 & ram_read_en $end
$var wire 4 ' ram_address [3:0] $end
$var wire 1 ( overflow $end
$var wire 4 ) opcode [3:0] $end
$var wire 1 * negative $end
$var wire 8 + alu_out [7:0] $end
$var wire 8 , alu_in_B [7:0] $end
$var wire 8 - alu_in_A [7:0] $end
$scope module ALU $end
$var wire 4 . opcode [3:0] $end
$var wire 8 / alu_in_B [7:0] $end
$var wire 8 0 alu_in_A [7:0] $end
$var reg 8 1 alu_out [7:0] $end
$var reg 1 2 extra $end
$var reg 1 * negative $end
$var reg 1 ( overflow $end
$var reg 1 $ zero $end
$upscope $end
$scope module CONTROL_UNIT $end
$var wire 8 3 alu_out [7:0] $end
$var wire 1 ! clk $end
$var wire 1 * negative $end
$var wire 1 ( overflow $end
$var wire 8 4 ram_data [7:0] $end
$var wire 1 # rst $end
$var wire 8 5 test_Register0 [7:0] $end
$var wire 8 6 test_Register1 [7:0] $end
$var wire 8 7 test_Register2 [7:0] $end
$var wire 8 8 test_Register3 [7:0] $end
$var wire 1 $ zero $end
$var reg 4 9 PC [3:0] $end
$var reg 8 : alu_in_A [7:0] $end
$var reg 8 ; alu_in_B [7:0] $end
$var reg 4 < opcode [3:0] $end
$var reg 4 = ram_address [3:0] $end
$var reg 1 & ram_read_en $end
$var reg 1 % ram_write_en $end
$var reg 3 > state [2:0] $end
$upscope $end
$scope module RAM $end
$var wire 8 ? ram_13 [7:0] $end
$var wire 4 @ ram_address [3:0] $end
$var wire 8 A ram_data [7:0] $end
$var wire 1 & ram_read_en $end
$var wire 1 % ram_write_en $end
$upscope $end
$upscope $end
$upscope $end
$enddefinitions $end
#0
$dumpvars
bz A
b0 @
b0 ?
b1 >
b0 =
b0 <
b0 ;
b0 :
b0 9
b0 8
b0 7
b0 6
b0 5
bz 4
bz 3
02
bz 1
b0 0
b0 /
b0 .
b0 -
b0 ,
bz +
0*
b0 )
0(
b0 '
0&
0%
0$
1#
bz "
0!
$end
#100
0#
#150
b101110 "
b101110 4
b101110 A
bz )
bz .
bz <
1&
1!
#200
0!
#250
b10 >
b1 9
b10 )
b10 .
b10 <
1!
#300
0!
#350
b1 "
b1 4
b1 A
b100 >
b1110 '
b1110 =
b1110 @
1!
#400
0!
#450
b11111 "
b11111 4
b11111 A
b1 >
b1 '
b1 =
b1 @
b1 5
1!
#500
0!
#550
b10 >
b10 9
b1 )
b1 .
b1 <
1!
#600
0!
#650
b1 "
b1 4
b1 A
b100 >
b1111 '
b1111 =
b1111 @
1!
#700
0!
#750
b10000100 "
b10000100 4
b10000100 A
b1 >
b10 '
b10 =
b10 @
b1 6
1!
#800
0!
#850
1$
b0 +
b0 1
b0 3
b10 >
b11 9
b1000 )
b1000 .
b1000 <
1!
#900
0!
#950
0$
b10 +
b10 1
b10 3
b100 >
b1 ,
b1 /
b1 ;
b1 -
b1 0
b1 :
1!
#1000
0!
#1050
b1001101 "
b1001101 4
b1001101 A
b1 >
b11 '
b11 =
b11 @
b10 5
1!
#1100
0!
#1150
bz +
bz 1
bz 3
b10 >
b100 9
b100 )
b100 .
b100 <
1!
#1200
0!
#1250
b10 ?
b10 "
b10 4
b10 A
b100 >
1%
0&
b1101 '
b1101 =
b1101 @
1!
#1300
0!
#1350
b10100010 "
b10100010 4
b10100010 A
b1 >
b100 '
b100 =
b100 @
0%
1&
1!
#1400
0!
#1450
b10 >
b101 9
b1010 )
b1010 .
b1010 <
1!
#1500
0!
#1550
b100 >
b10 9
1!
#1600
0!
#1650
b10000100 "
b10000100 4
b10000100 A
b1 >
b10 '
b10 =
b10 @
1!
#1700
0!
#1750
b10 +
b10 1
b10 3
b10 >
b11 9
b1000 )
b1000 .
b1000 <
1!
#1800
0!
#1850
b11 +
b11 1
b11 3
b100 >
b10 ,
b10 /
b10 ;
1!
#1900
0!
#1950
b1001101 "
b1001101 4
b1001101 A
b1 >
b11 '
b11 =
b11 @
b11 5
1!
#2000
0!
#2050
bz +
bz 1
bz 3
b10 >
b100 9
b100 )
b100 .
b100 <
1!
#2100
0!
#2150
b11 ?
b11 "
b11 4
b11 A
b100 >
1%
0&
b1101 '
b1101 =
b1101 @
1!
#2200
0!
#2250
b10100010 "
b10100010 4
b10100010 A
b1 >
b100 '
b100 =
b100 @
0%
1&
1!
#2300
0!
#2350
b10 >
b101 9
b1010 )
b1010 .
b1010 <
1!
#2400
0!
#2450
b100 >
b10 9
1!
#2500
0!
#2550
b10000100 "
b10000100 4
b10000100 A
b1 >
b10 '
b10 =
b10 @
1!
#2600
0!
#2650
b11 +
b11 1
b11 3
b10 >
b11 9
b1000 )
b1000 .
b1000 <
1!
#2700
0!
#2750
b100 +
b100 1
b100 3
b100 >
b11 ,
b11 /
b11 ;
1!
#2800
0!
#2850
b1001101 "
b1001101 4
b1001101 A
b1 >
b11 '
b11 =
b11 @
b100 5
1!
#2900
0!
#2950
bz +
bz 1
bz 3
b10 >
b100 9
b100 )
b100 .
b100 <
1!
#3000
0!
#3050
b100 ?
b100 "
b100 4
b100 A
b100 >
1%
0&
b1101 '
b1101 =
b1101 @
1!
#3100
0!
#3150
b10100010 "
b10100010 4
b10100010 A
b1 >
b100 '
b100 =
b100 @
0%
1&
1!
#3200
0!
#3250
b10 >
b101 9
b1010 )
b1010 .
b1010 <
1!
#3300
0!
#3350
b100 >
b10 9
1!
#3400
0!
#3450
b10000100 "
b10000100 4
b10000100 A
b1 >
b10 '
b10 =
b10 @
1!
#3500
0!
#3550
b100 +
b100 1
b100 3
b10 >
b11 9
b1000 )
b1000 .
b1000 <
1!
#3600
0!
#3650
b101 +
b101 1
b101 3
b100 >
b100 ,
b100 /
b100 ;
1!
#3700
0!
#3750
b1001101 "
b1001101 4
b1001101 A
b1 >
b11 '
b11 =
b11 @
b101 5
1!
#3800
0!
#3850
bz +
bz 1
bz 3
b10 >
b100 9
b100 )
b100 .
b100 <
1!
#3900
0!
#3950
b101 ?
b101 "
b101 4
b101 A
b100 >
1%
0&
b1101 '
b1101 =
b1101 @
1!
#4000
0!
#4050
b10100010 "
b10100010 4
b10100010 A
b1 >
b100 '
b100 =
b100 @
0%
1&
1!
#4100
0!
#4150
b10 >
b101 9
b1010 )
b1010 .
b1010 <
1!
#4200
0!
#4250
b100 >
b10 9
1!
#4300
0!
#4350
b10000100 "
b10000100 4
b10000100 A
b1 >
b10 '
b10 =
b10 @
1!
#4400
0!
#4450
b101 +
b101 1
b101 3
b10 >
b11 9
b1000 )
b1000 .
b1000 <
1!
#4500
0!
#4550
b110 +
b110 1
b110 3
b100 >
b101 ,
b101 /
b101 ;
1!
#4600
0!
#4650
b1001101 "
b1001101 4
b1001101 A
b1 >
b11 '
b11 =
b11 @
b110 5
1!
#4700
0!
#4750
bz +
bz 1
bz 3
b10 >
b100 9
b100 )
b100 .
b100 <
1!
#4800
0!
#4850
b110 ?
b110 "
b110 4
b110 A
b100 >
1%
0&
b1101 '
b1101 =
b1101 @
1!
#4900
0!
#4950
b10100010 "
b10100010 4
b10100010 A
b1 >
b100 '
b100 =
b100 @
0%
1&
1!
#5000
0!
#5050
b10 >
b101 9
b1010 )
b1010 .
b1010 <
1!
#5100
0!
#5150
b100 >
b10 9
1!
#5200
0!
#5250
b10000100 "
b10000100 4
b10000100 A
b1 >
b10 '
b10 =
b10 @
1!
#5300
0!
#5350
b110 +
b110 1
b110 3
b10 >
b11 9
b1000 )
b1000 .
b1000 <
1!
#5400
0!
#5450
b111 +
b111 1
b111 3
b100 >
b110 ,
b110 /
b110 ;
1!
#5500
0!
#5550
b1001101 "
b1001101 4
b1001101 A
b1 >
b11 '
b11 =
b11 @
b111 5
1!
#5600
0!
#5650
bz +
bz 1
bz 3
b10 >
b100 9
b100 )
b100 .
b100 <
1!
#5700
0!
#5750
b111 ?
b111 "
b111 4
b111 A
b100 >
1%
0&
b1101 '
b1101 =
b1101 @
1!
#5800
0!
#5850
b10100010 "
b10100010 4
b10100010 A
b1 >
b100 '
b100 =
b100 @
0%
1&
1!
#5900
0!
#5950
b10 >
b101 9
b1010 )
b1010 .
b1010 <
1!
#6000
0!
#6050
b100 >
b10 9
1!
#6100
0!
#6150
b10000100 "
b10000100 4
b10000100 A
b1 >
b10 '
b10 =
b10 @
1!
#6200
0!
#6250
b111 +
b111 1
b111 3
b10 >
b11 9
b1000 )
b1000 .
b1000 <
1!
#6300
0!
#6350
b1000 +
b1000 1
b1000 3
b100 >
b111 ,
b111 /
b111 ;
1!
#6400
0!
#6450
b1001101 "
b1001101 4
b1001101 A
b1 >
b11 '
b11 =
b11 @
b1000 5
1!
#6500
0!
#6550
bz +
bz 1
bz 3
b10 >
b100 9
b100 )
b100 .
b100 <
1!
#6600
0!
#6650
b1000 ?
b1000 "
b1000 4
b1000 A
b100 >
1%
0&
b1101 '
b1101 =
b1101 @
1!
#6700
0!
#6750
b10100010 "
b10100010 4
b10100010 A
b1 >
b100 '
b100 =
b100 @
0%
1&
1!
#6800
0!
#6850
b10 >
b101 9
b1010 )
b1010 .
b1010 <
1!
#6900
0!
#6950
b100 >
b10 9
1!
#7000
0!
#7050
b10000100 "
b10000100 4
b10000100 A
b1 >
b10 '
b10 =
b10 @
1!
#7100
0!
#7150
b1000 +
b1000 1
b1000 3
b10 >
b11 9
b1000 )
b1000 .
b1000 <
1!
#7200
0!
#7250
b1001 +
b1001 1
b1001 3
b100 >
b1000 ,
b1000 /
b1000 ;
1!
#7300
0!
#7350
b1001101 "
b1001101 4
b1001101 A
b1 >
b11 '
b11 =
b11 @
b1001 5
1!
#7400
0!
#7450
bz +
bz 1
bz 3
b10 >
b100 9
b100 )
b100 .
b100 <
1!
#7500
0!
#7550
b1001 ?
b1001 "
b1001 4
b1001 A
b100 >
1%
0&
b1101 '
b1101 =
b1101 @
1!
#7600
0!
#7650
b10100010 "
b10100010 4
b10100010 A
b1 >
b100 '
b100 =
b100 @
0%
1&
1!
#7700
0!
#7750
b10 >
b101 9
b1010 )
b1010 .
b1010 <
1!
#7800
0!
#7850
b100 >
b10 9
1!
#7900
0!
#7950
b10000100 "
b10000100 4
b10000100 A
b1 >
b10 '
b10 =
b10 @
1!
#8000
0!
#8050
b1001 +
b1001 1
b1001 3
b10 >
b11 9
b1000 )
b1000 .
b1000 <
1!
#8100
0!
#8150
b1010 +
b1010 1
b1010 3
b100 >
b1001 ,
b1001 /
b1001 ;
1!
#8200
0!
#8250
b1001101 "
b1001101 4
b1001101 A
b1 >
b11 '
b11 =
b11 @
b1010 5
1!
#8300
0!
#8350
bz +
bz 1
bz 3
b10 >
b100 9
b100 )
b100 .
b100 <
1!
#8400
0!
#8450
b1010 ?
b1010 "
b1010 4
b1010 A
b100 >
1%
0&
b1101 '
b1101 =
b1101 @
1!
#8500
0!
#8550
b10100010 "
b10100010 4
b10100010 A
b1 >
b100 '
b100 =
b100 @
0%
1&
1!
#8600
0!
#8650
b10 >
b101 9
b1010 )
b1010 .
b1010 <
1!
#8700
0!
#8750
b100 >
b10 9
1!
#8800
0!
#8850
b10000100 "
b10000100 4
b10000100 A
b1 >
b10 '
b10 =
b10 @
1!
#8900
0!
#8950
b1010 +
b1010 1
b1010 3
b10 >
b11 9
b1000 )
b1000 .
b1000 <
1!
#9000
0!
#9050
b1011 +
b1011 1
b1011 3
b100 >
b1010 ,
b1010 /
b1010 ;
1!
#9100
0!
#9150
b1001101 "
b1001101 4
b1001101 A
b1 >
b11 '
b11 =
b11 @
b1011 5
1!
#9200
0!
#9250
bz +
bz 1
bz 3
b10 >
b100 9
b100 )
b100 .
b100 <
1!
#9300
0!
#9350
b1011 ?
b1011 "
b1011 4
b1011 A
b100 >
1%
0&
b1101 '
b1101 =
b1101 @
1!
#9400
0!
#9450
b10100010 "
b10100010 4
b10100010 A
b1 >
b100 '
b100 =
b100 @
0%
1&
1!
#9500
0!
#9550
b10 >
b101 9
b1010 )
b1010 .
b1010 <
1!
#9600
0!
#9650
b100 >
b10 9
1!
#9700
0!
#9750
b10000100 "
b10000100 4
b10000100 A
b1 >
b10 '
b10 =
b10 @
1!
#9800
0!
#9850
b1011 +
b1011 1
b1011 3
b10 >
b11 9
b1000 )
b1000 .
b1000 <
1!
#9900
0!
#9950
b1100 +
b1100 1
b1100 3
b100 >
b1011 ,
b1011 /
b1011 ;
1!
#10000
0!
#10050
b1001101 "
b1001101 4
b1001101 A
b1 >
b11 '
b11 =
b11 @
b1100 5
1!
#10100
0!
#10150
bz +
bz 1
bz 3
b10 >
b100 9
b100 )
b100 .
b100 <
1!
#10200
0!
#10250
b1100 ?
b1100 "
b1100 4
b1100 A
b100 >
1%
0&
b1101 '
b1101 =
b1101 @
1!
#10300
0!
#10350
b10100010 "
b10100010 4
b10100010 A
b1 >
b100 '
b100 =
b100 @
0%
1&
1!
#10400
0!
#10450
b10 >
b101 9
b1010 )
b1010 .
b1010 <
1!
#10500
0!
#10550
b100 >
b10 9
1!
#10600
0!
#10650
b10000100 "
b10000100 4
b10000100 A
b1 >
b10 '
b10 =
b10 @
1!
#10700
0!
#10750
b1100 +
b1100 1
b1100 3
b10 >
b11 9
b1000 )
b1000 .
b1000 <
1!
#10800
0!
#10850
b1101 +
b1101 1
b1101 3
b100 >
b1100 ,
b1100 /
b1100 ;
1!
#10900
0!
#10950
b1001101 "
b1001101 4
b1001101 A
b1 >
b11 '
b11 =
b11 @
b1101 5
1!
#11000
0!
#11050
bz +
bz 1
bz 3
b10 >
b100 9
b100 )
b100 .
b100 <
1!
#11100
0!
#11150
b1101 ?
b1101 "
b1101 4
b1101 A
b100 >
1%
0&
b1101 '
b1101 =
b1101 @
1!
#11200
0!
#11250
b10100010 "
b10100010 4
b10100010 A
b1 >
b100 '
b100 =
b100 @
0%
1&
1!
#11300
0!
#11350
b10 >
b101 9
b1010 )
b1010 .
b1010 <
1!
#11400
0!
#11450
b100 >
b10 9
1!
#11500
0!
#11550
b10000100 "
b10000100 4
b10000100 A
b1 >
b10 '
b10 =
b10 @
1!
#11600
0!
#11650
b1101 +
b1101 1
b1101 3
b10 >
b11 9
b1000 )
b1000 .
b1000 <
1!
#11700
0!
#11750
b1110 +
b1110 1
b1110 3
b100 >
b1101 ,
b1101 /
b1101 ;
1!
#11800
0!
#11850
b1001101 "
b1001101 4
b1001101 A
b1 >
b11 '
b11 =
b11 @
b1110 5
1!
#11900
0!
#11950
bz +
bz 1
bz 3
b10 >
b100 9
b100 )
b100 .
b100 <
1!
#12000
0!
#12050
b1110 ?
b1110 "
b1110 4
b1110 A
b100 >
1%
0&
b1101 '
b1101 =
b1101 @
1!
#12100
0!
#12150
b10100010 "
b10100010 4
b10100010 A
b1 >
b100 '
b100 =
b100 @
0%
1&
1!
#12200
0!
#12250
b10 >
b101 9
b1010 )
b1010 .
b1010 <
1!
#12300
0!
#12350
b100 >
b10 9
1!
#12400
0!
#12450
b10000100 "
b10000100 4
b10000100 A
b1 >
b10 '
b10 =
b10 @
1!
#12500
0!
#12550
b1110 +
b1110 1
b1110 3
b10 >
b11 9
b1000 )
b1000 .
b1000 <
1!
#12600
0!
#12650
b1111 +
b1111 1
b1111 3
b100 >
b1110 ,
b1110 /
b1110 ;
1!
#12700
0!
#12750
b1001101 "
b1001101 4
b1001101 A
b1 >
b11 '
b11 =
b11 @
b1111 5
1!
#12800
0!
#12850
bz +
bz 1
bz 3
b10 >
b100 9
b100 )
b100 .
b100 <
1!
#12900
0!
#12950
b1111 ?
b1111 "
b1111 4
b1111 A
b100 >
1%
0&
b1101 '
b1101 =
b1101 @
1!
#13000
0!
#13050
b10100010 "
b10100010 4
b10100010 A
b1 >
b100 '
b100 =
b100 @
0%
1&
1!
#13100
0!
#13150
b10 >
b101 9
b1010 )
b1010 .
b1010 <
1!
#13200
0!
#13250
b100 >
b10 9
1!
#13300
0!
#13350
b10000100 "
b10000100 4
b10000100 A
b1 >
b10 '
b10 =
b10 @
1!
#13400
0!
#13450
b1111 +
b1111 1
b1111 3
b10 >
b11 9
b1000 )
b1000 .
b1000 <
1!
#13500
0!
#13550
b10000 +
b10000 1
b10000 3
b100 >
b1111 ,
b1111 /
b1111 ;
1!
#13600
0!
#13650
b1001101 "
b1001101 4
b1001101 A
b1 >
b11 '
b11 =
b11 @
b10000 5
1!
#13700
0!
#13750
bz +
bz 1
bz 3
b10 >
b100 9
b100 )
b100 .
b100 <
1!
#13800
0!
#13850
b10000 ?
b10000 "
b10000 4
b10000 A
b100 >
1%
0&
b1101 '
b1101 =
b1101 @
1!
#13900
0!
#13950
b10100010 "
b10100010 4
b10100010 A
b1 >
b100 '
b100 =
b100 @
0%
1&
1!
#14000
0!
#14050
b10 >
b101 9
b1010 )
b1010 .
b1010 <
1!
#14100
0!
#14150
b100 >
b10 9
1!
#14200
0!
#14250
b10000100 "
b10000100 4
b10000100 A
b1 >
b10 '
b10 =
b10 @
1!
#14300
0!
#14350
b10000 +
b10000 1
b10000 3
b10 >
b11 9
b1000 )
b1000 .
b1000 <
1!
#14400
0!
#14450
b10001 +
b10001 1
b10001 3
b100 >
b10000 ,
b10000 /
b10000 ;
1!
#14500
0!
#14550
b1001101 "
b1001101 4
b1001101 A
b1 >
b11 '
b11 =
b11 @
b10001 5
1!
#14600
0!
#14650
bz +
bz 1
bz 3
b10 >
b100 9
b100 )
b100 .
b100 <
1!
#14700
0!
#14750
b10001 ?
b10001 "
b10001 4
b10001 A
b100 >
1%
0&
b1101 '
b1101 =
b1101 @
1!
#14800
0!
#14850
b10100010 "
b10100010 4
b10100010 A
b1 >
b100 '
b100 =
b100 @
0%
1&
1!
#14900
0!
#14950
b10 >
b101 9
b1010 )
b1010 .
b1010 <
1!
#15000
0!
#15050
b100 >
b10 9
1!
#15100
0!
#15150
b10000100 "
b10000100 4
b10000100 A
b1 >
b10 '
b10 =
b10 @
1!
#15200
0!
#15250
b10001 +
b10001 1
b10001 3
b10 >
b11 9
b1000 )
b1000 .
b1000 <
1!
#15300
0!
#15350
b10010 +
b10010 1
b10010 3
b100 >
b10001 ,
b10001 /
b10001 ;
1!
#15400
0!
#15450
b1001101 "
b1001101 4
b1001101 A
b1 >
b11 '
b11 =
b11 @
b10010 5
1!
#15500
0!
#15550
bz +
bz 1
bz 3
b10 >
b100 9
b100 )
b100 .
b100 <
1!
#15600
0!
#15650
b10010 ?
b10010 "
b10010 4
b10010 A
b100 >
1%
0&
b1101 '
b1101 =
b1101 @
1!
#15700
0!
#15750
b10100010 "
b10100010 4
b10100010 A
b1 >
b100 '
b100 =
b100 @
0%
1&
1!
#15800
0!
#15850
b10 >
b101 9
b1010 )
b1010 .
b1010 <
1!
#15900
0!
#15950
b100 >
b10 9
1!
#16000
0!
#16050
b10000100 "
b10000100 4
b10000100 A
b1 >
b10 '
b10 =
b10 @
1!
#16100
0!
#16150
b10010 +
b10010 1
b10010 3
b10 >
b11 9
b1000 )
b1000 .
b1000 <
1!
#16200
0!
#16250
b10011 +
b10011 1
b10011 3
b100 >
b10010 ,
b10010 /
b10010 ;
1!
#16300
0!
