control_unit.v
`timescale 1ns / 1ps
module control_unit(clk, rst, ram_data, ram_read_en, ram_write_en, ram_address, opcode, alu_in_A, alu_in_B, alu_out, overflow, zero, negative);

input clk, rst, overflow, zero, negative ;   		// clock, reset
input [7:0] alu_out;

output reg ram_read_en, ram_write_en;
output reg [7:0] alu_in_A, alu_in_B;
output reg [3:0] opcode;
output reg [3:0] ram_address;

// 相当于control_unit和ram之间的databus
inout [7:0] ram_data;


reg [7:0] Register[0:3];
reg [3:0] PC;
reg [2:0] state;

// 仅做仿真时观察波形使用：begin
wire [7:0] test_Register0, test_Register1, test_Register2, test_Register3; 
assign test_Register0 = Register[0];
assign test_Register1 = Register[1];
assign test_Register2 = Register[2];
assign test_Register3 = Register[3];
// 仅做仿真时观察波形使用：end
// 有关仿真时数组再iverilog的显示问题，参考了
// https://stackoverflow.com/questions/20317820/icarus-verilog-dump-memory-array-dumpvars
// 原因：iverilog 仿真时就是不能 dump 数组

// 相当于control_unit和ram之间的databus
assign ram_data = (ram_write_en)? Register[0]:8'hzz;

// instruction code
parameter 	HALT     = 4'b0000,
			LOAD_A   = 4'b0010,
			LOAD_B   = 4'b0001,
			STORE_A  = 4'b0100,
			ADD      = 4'b1000,
			SUB      = 4'b1001,
			JUMP     = 4'b1010,
			JUMP_NEG = 4'b1011,
			WIDTH    = 8,
			MSB      = WIDTH - 1;

// state encoding one-hot			 
parameter	S0 = 3'b001,
			S1 = 3'b010,
			S2 = 3'b100;

initial
	begin
		state = S0;
		PC = 4'b0000;
		ram_address = 4'b0000;
		opcode = HALT;
		alu_in_A	= 8'b0000_0000;
		alu_in_B 	= 8'b0000_0000;
		Register[0] = 8'b0000_0000;
		Register[1] = 8'b0000_0000;
		Register[2] = 8'b0000_0000;
		Register[3] = 8'b0000_0000;
		ram_read_en = 1'b0;
		ram_write_en = 1'b0;

		//通用寄存器初始化
	end
    


always@(posedge clk)
begin
	case(state)
	// 取指令
	S0: begin
		ram_address <= PC;
		ram_read_en <= 1'b1;
		ram_write_en<= 1'b0;
		opcode <= ram_data[7:4];
		if (opcode == HALT || rst) begin
			state <= S0;
			
		end else begin
			PC <= PC + 1;
			state <= S1;

		end
	end
	// 指令译码(对号入座)和执行指令
	S1: begin
		if ((opcode == LOAD_A) || (opcode == LOAD_B)) begin
			ram_address <= ram_data[3:0];
			ram_read_en <= 1'b1;
			ram_write_en<= 1'b0;
			state <= S2;

			
		end else if ((opcode == ADD) || (opcode == SUB)) begin
			alu_in_B <= Register[ram_data[3:2]];
			alu_in_A <= Register[ram_data[1:0]];
			state <= S2;
			
			
		end else if (opcode == JUMP) begin
			PC <= ram_data[3:0];
			state <= S2;

		end else if (opcode == JUMP_NEG) begin
			PC <= negative ? ram_data[3:0] : (PC);
			state <= S2;
			
		end else if (opcode == STORE_A) begin
			ram_address <= ram_data[3:0];
			ram_read_en <= 1'b0;
			ram_write_en <= 1'b1;
			state <= S2;

		end else begin
			state <= S0;
		end
		
	end
	// 写入寄存器或RAM以及准备复位
	S2: begin
		case (opcode)
			LOAD_A: begin 
				Register[0] <= ram_data[7:0];
				ram_address <= PC;
				state <= S0;
			end
			LOAD_B: begin
				Register[1] <= ram_data[7:0];
				ram_address <= PC;
				state <= S0;
			end
			ADD: begin
				Register[ram_data[1:0]] <= alu_out;
				ram_address <= PC;
				state <= S0; 
			end
			SUB: begin
				Register[ram_data[1:0]] <= alu_out;
				ram_address <= PC;
				state <= S0;
				
			end
			STORE_A: begin
				ram_read_en <= 1'b1;
				ram_write_en <= 1'b0;
				ram_address <= PC;
				
				state <= S0;
			end
			JUMP: begin
				ram_address <= PC;
				state <= S0;
			end
			JUMP_NEG: begin
				ram_address <= PC;
				state <= S0;
			end

			default: state <= S0;
		endcase
	end

	default: begin
		state <= S0;
		ram_read_en  <= 1'b0;
		ram_write_en <= 1'b0;
		ram_address <= 4'b0000;
		opcode <= HALT;
	end
endcase
end

endmodule

ram.v
`timescale 1ns / 1ps
/////////////////////////////////////////////////////////////
module ram(ram_data, ram_read_en, ram_write_en, ram_address);

input ram_read_en, ram_write_en;
input [3:0] ram_address;

inout [7:0] ram_data;

reg [7:0] ram[0:15];

//仅做仿真时观察波形使用：begin
wire [7:0] ram_13; 
assign ram_13 = ram[13];
//仅做仿真时观察波形使用：end

// //第一个程序，计算机速成课episode 7
// //3+14 = 17
// initial 
// 	begin
// 		ram[0] = 8'b0010_1110; // LOAD_A 14
// 		ram[1] = 8'b0001_1111; // LOAD_B 15
// 		ram[2] = 8'b1000_0100; // ADD B A
// 		ram[3] = 8'b0100_1101; // STORE_A 13
// 		ram[4] = 8'b0000_0000;
// 		ram[5] = 8'b0000_0000;
// 		ram[6] = 8'b0000_0000;
// 		ram[7] = 8'b0000_0000;
// 		ram[8] = 8'b0000_0000;
// 		ram[9] = 8'b0000_0000;
// 		ram[10]= 8'b0000_0000;
// 		ram[11]= 8'b0000_0000;
// 		ram[12]= 8'b0000_0000;
// 		ram[13]= 8'b0000_0000;
// 		ram[14]= 8'b0000_0011; // 3
// 		ram[15]= 8'b0000_1110; // 14
// 	end

// //第二个程序，计算机速成课episode 8
// //1+1,2+1,...
// initial 
// 	begin
// 		ram[0] = 8'b0010_1110; // LOAD_A 14
// 		ram[1] = 8'b0001_1111; // LOAD_B 15
// 		ram[2] = 8'b1000_0100; // ADD B A
// 		ram[3] = 8'b0100_1101; // STORE_A 13
// 		ram[4] = 8'b1010_0010; // JUMP 2
// 		ram[5] = 8'b0000_0000;
// 		ram[6] = 8'b0000_0000;
// 		ram[7] = 8'b0000_0000;
// 		ram[8] = 8'b0000_0000;
// 		ram[9] = 8'b0000_0000;
// 		ram[10]= 8'b0000_0000;
// 		ram[11]= 8'b0000_0000;
// 		ram[12]= 8'b0000_0000;
// 		ram[13]= 8'b0000_0000;
// 		ram[14]= 8'b0000_0001; // 1
// 		ram[15]= 8'b0000_0001; // 1
// 	end

// 第三个程序，计算机速成课episode 8
// 11 mod 5 == 1
initial 
	begin
		ram[0] = 8'b0010_1110; // LOAD_A 14
		ram[1] = 8'b0001_1111; // LOAD_B 15
		ram[2] = 8'b1001_0100; // SUB B A
		ram[3] = 8'b1011_0101; // JUMP_NEG 5
		ram[4] = 8'b1010_0010; // JUMP 2
		ram[5] = 8'b1000_0100; // ADD B A
		ram[6] = 8'b0100_1101; // STORE_A 13
		ram[7] = 8'b0000_0000; // HALT
		ram[8] = 8'b0000_0000;
		ram[9] = 8'b0000_0000;
		ram[10]= 8'b0000_0000;
		ram[11]= 8'b0000_0000;
		ram[12]= 8'b0000_0000;
		ram[13]= 8'b0000_0000;
		ram[14]= 8'b0000_1011; // 11
		ram[15]= 8'b0000_0101; // 5
	end


assign ram_data = (ram_read_en)? ram[ram_address]:8'hzz;		// read data from RAM

//尝试了always @(posedge ram_write_en) //失败，发现赋值结果为高阻态
always @(ram_write_en or ram_data) begin	// write data to RAM
	if (ram_write_en) ram[ram_address] <= ram_data;
end

endmodule

alu.v
`timescale 1ns / 1ps
//////////////////////////////////////////////////////////////
module alu(opcode, alu_in_A, alu_in_B, alu_out, overflow, zero, negative);//  arithmetic logic unit
input [3:0] opcode;
input [7:0] alu_in_A, alu_in_B;
output reg [7:0] alu_out;
output reg overflow;
output reg zero;
output reg negative;

reg extra;

parameter 	HALT     = 4'b0000,
			LOAD_A   = 4'b0010,
			LOAD_B   = 4'b0001,
			STORE_A  = 4'b0100,
			ADD      = 4'b1000,
			SUB      = 4'b1001,
			JUMP     = 4'b1010,
			JUMP_NEG = 4'b1011,
			WIDTH    = 8,
			MSB      = WIDTH - 1;


initial
	begin
		alu_out = 8'b00000000;
		overflow = 1'b0;
		zero = 1'b0;
		negative = 1'b0;
		extra = 1'b0;

		//通用寄存器初始化
	end

always @(*) begin
		case (opcode)
		ADD:
		begin
			{extra, alu_out} = {alu_in_A[MSB], alu_in_A} + {alu_in_B[MSB], alu_in_B};
			overflow  = ({extra, alu_out[MSB]} == 2'b01) || ({extra, alu_out[MSB]} == 2'b10);
			zero = alu_out ? 0 : 1;
			negative = alu_out[MSB];
		end
		SUB:
		begin
			if (!alu_in_B) begin
				alu_out = alu_in_A;
				overflow  = 1'b0;
				zero = alu_out ? 0 : 1;
				negative = alu_out[MSB];
			end else begin
				{extra, alu_out} = {alu_in_A[MSB], alu_in_A} + ~{alu_in_B[MSB], alu_in_B} + 9'b000000001;
				overflow  = ({extra, alu_out[MSB]} == 2'b01) || ({extra, alu_out[MSB]} == 2'b10);
				zero = alu_out ? 0 : 1;
				negative = alu_out[MSB];
			end
		end

		default:	alu_out = 8'bzzzz_zzzz;
		endcase
end

endmodule

core.v
`timescale 1ns / 1ps
module core(clk, rst);	// Top-level entity(except core-tb)
input clk, rst;

wire ram_read_en, ram_write_en;
wire overflow, zero, negative;

wire[7:0] ram_data;
wire[7:0] alu_in_A, alu_in_B, alu_out;
wire[3:0] opcode, ram_address;

//module alu(opcode, alu_in_A, alu_in_B, alu_out, overflow, zero, negative);
alu ALU(.opcode(opcode), .alu_in_A(alu_in_A), .alu_in_B(alu_in_B), .alu_out(alu_out), .overflow(overflow), .zero(zero), .negative(negative));

//module ram(ram_data, ram_read_en, ram_write_en, ram_address);
ram RAM(.ram_data(ram_data), .ram_read_en(ram_read_en), .ram_write_en(ram_write_en), .ram_address(ram_address));


//module control_unit(clk, rst, ram_data, ram_read_en, ram_write_en, ram_address, opcode, alu_in_A, alu_in_B, alu_out, overflow, zero, negative);
control_unit CONTROL_UNIT(.clk(clk), 
					.rst(rst), 
					.ram_data(ram_data), 
					.ram_read_en(ram_read_en), 
					.ram_write_en(ram_write_en), 
					.ram_address(ram_address), 
					.opcode(opcode), 
					.alu_in_A(alu_in_A), 
					.alu_in_B(alu_in_B), 
					.alu_out(alu_out), 
					.overflow(overflow), 
					.zero(zero), 
					.negative(negative)
					);
					

endmodule

core_testbench.v
`timescale 1ps / 1ps
module core_testbench; 

reg rst; 
reg clk; 

initial
	begin
    $dumpfile("test.vcd");
    $dumpvars(0,core1);
	end

initial
  begin
    clk <= 1'b0;
    # 150 ;
  repeat(9999)
  begin
    clk  = 1'b1;
    #50  clk  = 1'b0;
    #50  ;
  end
  clk  = 1'b1;
  # 50 ;
  end
initial
  begin
	  rst  = 1'b1  ;
	  # 100;
	  rst=1'b0;
	  # 9000 ;
  end
core core1(.clk(clk),.rst(rst));

initial
#1000000 $finish;
endmodule

第七集程序仿真波形结果/test.vcd
$date
	Tue May 19 12:28:40 2020
$end
$version
	Icarus Verilog
$end
$timescale
	1ps
$end
$scope module core_testbench $end
$scope module core1 $end
$var wire 1 ! clk $end
$var wire 8 " ram_data [7:0] $end
$var wire 1 # rst $end
$var wire 1 $ zero $end
$var wire 1 % ram_write_en $end
$var wire 1 & ram_read_en $end
$var wire 4 ' ram_address [3:0] $end
$var wire 1 ( overflow $end
$var wire 4 ) opcode [3:0] $end
$var wire 1 * negative $end
$var wire 8 + alu_out [7:0] $end
$var wire 8 , alu_in_B [7:0] $end
$var wire 8 - alu_in_A [7:0] $end
$scope module ALU $end
$var wire 4 . opcode [3:0] $end
$var wire 8 / alu_in_B [7:0] $end
$var wire 8 0 alu_in_A [7:0] $end
$var reg 8 1 alu_out [7:0] $end
$var reg 1 2 extra $end
$var reg 1 * negative $end
$var reg 1 ( overflow $end
$var reg 1 $ zero $end
$upscope $end
$scope module CONTROL_UNIT $end
$var wire 8 3 alu_out [7:0] $end
$var wire 1 ! clk $end
$var wire 1 * negative $end
$var wire 1 ( overflow $end
$var wire 8 4 ram_data [7:0] $end
$var wire 1 # rst $end
$var wire 8 5 test_Register0 [7:0] $end
$var wire 8 6 test_Register1 [7:0] $end
$var wire 8 7 test_Register2 [7:0] $end
$var wire 8 8 test_Register3 [7:0] $end
$var wire 1 $ zero $end
$var reg 4 9 PC [3:0] $end
$var reg 8 : alu_in_A [7:0] $end
$var reg 8 ; alu_in_B [7:0] $end
$var reg 4 < opcode [3:0] $end
$var reg 4 = ram_address [3:0] $end
$var reg 1 & ram_read_en $end
$var reg 1 % ram_write_en $end
$var reg 3 > state [2:0] $end
$upscope $end
$scope module RAM $end
$var wire 8 ? ram_13 [7:0] $end
$var wire 4 @ ram_address [3:0] $end
$var wire 8 A ram_data [7:0] $end
$var wire 1 & ram_read_en $end
$var wire 1 % ram_write_en $end
$upscope $end
$upscope $end
$upscope $end
$enddefinitions $end
#0
$dumpvars
bz A
b0 @
b0 ?
b1 >
b0 =
b0 <
b0 ;
b0 :
b0 9
b0 8
b0 7
b0 6
b0 5
bz 4
bz 3
02
bz 1
b0 0
b0 /
b0 .
b0 -
b0 ,
bz +
0*
b0 )
0(
b0 '
0&
0%
0$
1#
bz "
0!
$end
#100
0#
#150
b101110 "
b101110 4
b101110 A
bz )
bz .
bz <
1&
1!
#200
0!
#250
b10 >
b1 9
b10 )
b10 .
b10 <
1!
#300
0!
#350
b11 "
b11 4
b11 A
b100 >
b1110 '
b1110 =
b1110 @
1!
#400
0!
#450
b11111 "
b11111 4
b11111 A
b1 >
b1 '
b1 =
b1 @
b11 5
1!
#500
0!
#550
b10 >
b10 9
b1 )
b1 .
b1 <
1!
#600
0!
#650
b1110 "
b1110 4
b1110 A
b100 >
b1111 '
b1111 =
b1111 @
1!
#700
0!
#750
b10000100 "
b10000100 4
b10000100 A
b1 >
b10 '
b10 =
b10 @
b1110 6
1!
#800
0!
#850
1$
b0 +
b0 1
b0 3
b10 >
b11 9
b1000 )
b1000 .
b1000 <
1!
#900
0!
#950
0$
b10001 +
b10001 1
b10001 3
b100 >
b11 ,
b11 /
b11 ;
b1110 -
b1110 0
b1110 :
1!
#1000
0!
#1050
b1001101 "
b1001101 4
b1001101 A
b1 >
b11 '
b11 =
b11 @
b10001 5
1!
#1100
0!
#1150
bz +
bz 1
bz 3
b10 >
b100 9
b100 )
b100 .
b100 <
1!
#1200
0!
#1250
b10001 ?
b10001 "
b10001 4
b10001 A
b100 >
1%
0&
b1101 '
b1101 =
b1101 @
1!
#1300
0!
#1350
b0 "
b0 4
b0 A
b1 >
b100 '
b100 =
b100 @
0%
1&
1!
#1400
0!
#1450
b10 >
b101 9
b0 )
b0 .
b0 <
1!
#1500
0!
#1550
b1 >
1!
#1600
0!
#1650
b101 '
b101 =
b101 @
1!
